lazy_toolkit/__init__.py
lazy_toolkit/background_task.py
lazy_toolkit/decorator.py
lazy_toolkit/enum.py
lazy_toolkit/exception.py
lazy_toolkit/file.py
lazy_toolkit/lock_context.py
lazy_toolkit/logging.py
lazy_toolkit/misc.py
lazy_toolkit/mixin.py
lazy_toolkit/number.py
lazy_toolkit/string.py
lazy_toolkit/time.py
lazy_toolkit/timer_job.py
lazy_toolkit/http/__init__.py
lazy_toolkit/http/requester.py
lazy_toolkit/http/rest_response.py
lazy_toolkit/http/status_code.py
lazy_toolkit-0.0.3.dist-info/LICENSE
lazy_toolkit-0.0.3.dist-info/METADATA
lazy_toolkit-0.0.3.dist-info/WHEEL
lazy_toolkit-0.0.3.dist-info/top_level.txt
lazy_toolkit-0.0.3.dist-info/RECORD
